Workbook

Sheet Cover
A1: GS ERP — Master QA Test Plan
A2: System: https://test.tadgeeg.com | Plan author: QA Architect | Generated: 2026-04-23
A4: Purpose | B4: Executable, evidence-based test plan for a production-grade ERP. 320+ test cases across 7 phases + cross-cutting areas. Each case has clear steps, data, and expected outcome. Fill Status, Severity, and Evidence columns as you execute.
A5: Scope (included) | B5: Phase 1 Core Accounting • Phase 2 Sales & AR • Phase 3 Purchases & AP • Phase 4 Treasury • Phase 5 Inventory • Phase 6 Tax/Closing • Phase 7 Smart Finance/AI. Plus UI/UX, API, Security, Reporting Consistency, Data Integrity, Regression.
A6: Scope (excluded) | B6: Performance/load testing beyond basic latency spot-checks; formal penetration testing; SOC/ISO compliance audits. These require specialized tools/teams.
A7: How to execute | B7: 1) Go to Summary sheet — shows running counts live. 2) Open a Phase sheet. 3) Perform the Test Steps with the Test Data. 4) Compare actual vs Expected Result. 5) Record Actual Result, set Status (dropdown), attach Evidence (screenshot/file path/URL). 6) If Fail, set Severity. Add Notes. 7) P0 cases MUST all pass before Go-Live.
A8: Pass / Fail / Blocked / N/A | B8: Pass = Expected matched exactly. Fail = Deviation from Expected. Set Severity. Blocked = Cannot run due to missing access, data, or dependency. N/A = Feature not applicable to this deployment.
A9: Severity guide | B9: Critical = Data corruption, accounting imbalance, security breach, data leak between tenants. High = Broken major flow, incorrect totals, missing critical feature. Medium = Workaround exists, partial feature, non-critical UX. Low = Cosmetic.
A10: Hard-FAIL rules (per user instruction) | B10: Any mismatch between GL / TB / Reports / Subsidiary ledgers ⇒ phase FAIL. Permission bypass or cross-tenant data leak ⇒ phase FAIL. Posted entries mutable ⇒ phase FAIL. Closed-period posting accepted ⇒ phase FAIL. AR/AP/Inventory subsidiary ≠ GL ⇒ phase FAIL. AI that can mutate financial data directly ⇒ phase FAIL.
A11: Assumption policy | B11: Never mark a case Pass unless you actually verified the outcome. If unverifiable, mark Blocked with reason. The goal is evidence, not coverage theater.
A12: Findings from public-page pre-audit | B12: F-001 Branding inconsistency (domain vs 'GS ERP'). F-002 Password policy min=8 chars only, no complexity → P1 risk. F-003 No visible MFA on login → P0 risk for financial system. F-004 Self-service signup with no visible CAPTCHA → P2 risk. F-005 No language toggle on public pages. F-006 Remember-me without duration disclosure. See README.md for full analysis.

Sheet Summary
A1: Execution Summary (live counts)
A3: Phase / Area | B3: Total | C3: Not Run | D3: Pass | E3: Fail | F3: Blocked | G3: N/A | H3: Pass % | I3: P0 Fails
A4: Phase 1 Core Accounting | B4: =COUNTA('Phase 1 Core Accounting'!A4:A63) -> 60 | C4: =COUNTIF('Phase 1 Core Accounting'!J4:J63,"Not Run") -> 60 | D4: =COUNTIF('Phase 1 Core Accounting'!J4:J63,"Pass") -> 0 | E4: =COUNTIF('Phase 1 Core Accounting'!J4:J63,"Fail") -> 0 | F4: =COUNTIF('Phase 1 Core Accounting'!J4:J63,"Blocked") -> 0 | G4: =COUNTIF('Phase 1 Core Accounting'!J4:J63,"N/A") -> 0 | H4: =IFERROR(D4/(B4-G4),0) -> 0 | I4: =COUNTIFS('Phase 1 Core Accounting'!B4:B63,"P0",'Phase 1 Core Accounting'!J4:J63,"Fail") -> 0
A5: Phase 2 Sales & AR | B5: =COUNTA('Phase 2 Sales & AR'!A4:A48) -> 45 | C5: =COUNTIF('Phase 2 Sales & AR'!J4:J48,"Not Run") -> 45 | D5: =COUNTIF('Phase 2 Sales & AR'!J4:J48,"Pass") -> 0 | E5: =COUNTIF('Phase 2 Sales & AR'!J4:J48,"Fail") -> 0 | F5: =COUNTIF('Phase 2 Sales & AR'!J4:J48,"Blocked") -> 0 | G5: =COUNTIF('Phase 2 Sales & AR'!J4:J48,"N/A") -> 0 | H5: =IFERROR(D5/(B5-G5),0) -> 0 | I5: =COUNTIFS('Phase 2 Sales & AR'!B4:B48,"P0",'Phase 2 Sales & AR'!J4:J48,"Fail") -> 0
A6: Phase 3 Purchases & AP | B6: =COUNTA('Phase 3 Purchases & AP'!A4:A43) -> 40 | C6: =COUNTIF('Phase 3 Purchases & AP'!J4:J43,"Not Run") -> 40 | D6: =COUNTIF('Phase 3 Purchases & AP'!J4:J43,"Pass") -> 0 | E6: =COUNTIF('Phase 3 Purchases & AP'!J4:J43,"Fail") -> 0 | F6: =COUNTIF('Phase 3 Purchases & AP'!J4:J43,"Blocked") -> 0 | G6: =COUNTIF('Phase 3 Purchases & AP'!J4:J43,"N/A") -> 0 | H6: =IFERROR(D6/(B6-G6),0) -> 0 | I6: =COUNTIFS('Phase 3 Purchases & AP'!B4:B43,"P0",'Phase 3 Purchases & AP'!J4:J43,"Fail") -> 0
A7: Phase 4 Treasury | B7: =COUNTA('Phase 4 Treasury'!A4:A38) -> 35 | C7: =COUNTIF('Phase 4 Treasury'!J4:J38,"Not Run") -> 35 | D7: =COUNTIF('Phase 4 Treasury'!J4:J38,"Pass") -> 0 | E7: =COUNTIF('Phase 4 Treasury'!J4:J38,"Fail") -> 0 | F7: =COUNTIF('Phase 4 Treasury'!J4:J38,"Blocked") -> 0 | G7: =COUNTIF('Phase 4 Treasury'!J4:J38,"N/A") -> 0 | H7: =IFERROR(D7/(B7-G7),0) -> 0 | I7: =COUNTIFS('Phase 4 Treasury'!B4:B38,"P0",'Phase 4 Treasury'!J4:J38,"Fail") -> 0
A8: Phase 5 Inventory | B8: =COUNTA('Phase 5 Inventory'!A4:A43) -> 40 | C8: =COUNTIF('Phase 5 Inventory'!J4:J43,"Not Run") -> 40 | D8: =COUNTIF('Phase 5 Inventory'!J4:J43,"Pass") -> 0 | E8: =COUNTIF('Phase 5 Inventory'!J4:J43,"Fail") -> 0 | F8: =COUNTIF('Phase 5 Inventory'!J4:J43,"Blocked") -> 0 | G8: =COUNTIF('Phase 5 Inventory'!J4:J43,"N/A") -> 0 | H8: =IFERROR(D8/(B8-G8),0) -> 0 | I8: =COUNTIFS('Phase 5 Inventory'!B4:B43,"P0",'Phase 5 Inventory'!J4:J43,"Fail") -> 0
A9: Phase 6 Tax & Closing | B9: =COUNTA('Phase 6 Tax & Closing'!A4:A33) -> 30 | C9: =COUNTIF('Phase 6 Tax & Closing'!J4:J33,"Not Run") -> 30 | D9: =COUNTIF('Phase 6 Tax & Closing'!J4:J33,"Pass") -> 0 | E9: =COUNTIF('Phase 6 Tax & Closing'!J4:J33,"Fail") -> 0 | F9: =COUNTIF('Phase 6 Tax & Closing'!J4:J33,"Blocked") -> 0 | G9: =COUNTIF('Phase 6 Tax & Closing'!J4:J33,"N/A") -> 0 | H9: =IFERROR(D9/(B9-G9),0) -> 0 | I9: =COUNTIFS('Phase 6 Tax & Closing'!B4:B33,"P0",'Phase 6 Tax & Closing'!J4:J33,"Fail") -> 0
A10: Phase 7 Smart Finance | B10: =COUNTA('Phase 7 Smart Finance'!A4:A28) -> 25 | C10: =COUNTIF('Phase 7 Smart Finance'!J4:J28,"Not Run") -> 25 | D10: =COUNTIF('Phase 7 Smart Finance'!J4:J28,"Pass") -> 0 | E10: =COUNTIF('Phase 7 Smart Finance'!J4:J28,"Fail") -> 0 | F10: =COUNTIF('Phase 7 Smart Finance'!J4:J28,"Blocked") -> 0 | G10: =COUNTIF('Phase 7 Smart Finance'!J4:J28,"N/A") -> 0 | H10: =IFERROR(D10/(B10-G10),0) -> 0 | I10: =COUNTIFS('Phase 7 Smart Finance'!B4:B28,"P0",'Phase 7 Smart Finance'!J4:J28,"Fail") -> 0
A11: X-Cutting UI API Sec | B11: =COUNTA('X-Cutting UI API Sec'!A4:A49) -> 46 | C11: =COUNTIF('X-Cutting UI API Sec'!J4:J49,"Not Run") -> 46 | D11: =COUNTIF('X-Cutting UI API Sec'!J4:J49,"Pass") -> 0 | E11: =COUNTIF('X-Cutting UI API Sec'!J4:J49,"Fail") -> 0 | F11: =COUNTIF('X-Cutting UI API Sec'!J4:J49,"Blocked") -> 0 | G11: =COUNTIF('X-Cutting UI API Sec'!J4:J49,"N/A") -> 0 | H11: =IFERROR(D11/(B11-G11),0) -> 0 | I11: =COUNTIFS('X-Cutting UI API Sec'!B4:B49,"P0",'X-Cutting UI API Sec'!J4:J49,"Fail") -> 0
A12: TOTAL | B12: =SUM(B4:B11) -> 321 | C12: =SUM(C4:C11) -> 321 | D12: =SUM(D4:D11) -> 0 | E12: =SUM(E4:E11) -> 0 | F12: =SUM(F4:F11) -> 0 | G12: =SUM(G4:G11) -> 0 | H12: =IFERROR(D12/(B12-G12),0) -> 0 | I12: =SUM(I4:I11) -> 0
A15: Go / No-Go Rules
A16: • Any P0 fail → No-Go until fixed.
A17: • Any Critical severity fail → No-Go.
A18: • AR/AP/Inventory ledger vs GL mismatch → No-Go.
A19: • BS unbalanced (A ≠ L + E) → No-Go.
A20: • Posting in closed period allowed → No-Go.
A21: • Cross-tenant data leak → No-Go.
A22: • Overall pass rate < 95% on executed P0/P1 → No-Go.
A25: Final Verdict (manual):

Sheet Phase 1 Core Accounting
A1: Phase 1 — Core Accounting Foundation
A2: Total cases: 60 | Fill 'Status' (dropdown). 'Severity' applies only if Fail.
A3: Test ID | B3: Priority | C3: Category | D3: Module / Area | E3: Preconditions | F3: Test Steps | G3: Test Data | H3: Expected Result | I3: Actual Result | J3: Status | K3: Severity (if Fail) | L3: Evidence (URL/path) | M3: Tester | N3: Date | O3: Notes
A4: P1-ORG-001 | B4: P0 | C4: Positive | D4: Organizations | E4: User logged in as Admin | F4: 1) Open Settings > Companies 2) Click 'New Company' 3) Fill: Name, Country=SA, Currency=SAR, Tax No. 4) Save | G4: Name='QA Test Co', Country='Saudi Arabia', Currency='SAR', VAT='300000000000003' | H4: Company created, appears in list, assigned unique ID, audit log entry created | J4: Not Run
A5: P1-ORG-002 | B5: P1 | C5: Negative | D5: Organizations | E5: Admin logged in | F5: 1) New Company 2) Leave Name empty 3) Save | G5: Name='' | H5: Form rejects with clear validation error on Name field; no record created | J5: Not Run
A6: P1-ORG-003 | B6: P1 | C6: Negative | D6: Organizations | E6: Company 'QA Test Co' exists | F6: 1) Create another company with same Tax Number 2) Save | G6: VAT='300000000000003' (duplicate) | H6: System rejects duplicate VAT with specific error; no duplicate record | J6: Not Run
A7: P1-ORG-004 | B7: P2 | C7: Positive | D7: Organizations | E7: Company exists | F7: 1) Open company 2) Edit Name/Address 3) Save | G7: Change address | H7: Changes saved; audit log records old→new values and user | J7: Not Run
A8: P1-ORG-005 | B8: P1 | C8: Security | D8: Organizations | E8: User from Company A logged in | F8: 1) Inspect company list 2) Try to access Company B via URL manipulation (change ID) | G8: URL /companies/<other_id> | H8: Access denied (403) or resource not found (404); no data leak | J8: Not Run
A9: P1-BR-006 | B9: P1 | C9: Positive | D9: Branches | E9: Company exists | F9: 1) Settings > Branches > New 2) Fill Name, Code, Parent Company 3) Save | G9: Name='Main Branch', Code='MB-001' | H9: Branch created and tied to correct company | J9: Not Run
A10: P1-BR-007 | B10: P1 | C10: Negative | D10: Branches | E10: Branch MB-001 exists | F10: 1) Create branch with same Code 2) Save | G10: Code='MB-001' | H10: Rejected with duplicate-code error | J10: Not Run
A11: P1-BR-008 | B11: P2 | C11: Negative | D11: Branches | E11: Branch has transactions | F11: 1) Open branch 2) Click Delete | G11: — | H11: Delete blocked; system prompts to deactivate instead | J11: Not Run
A12: P1-BR-009 | B12: P1 | C12: Integration | D12: Branches | E12: Two branches exist | F12: 1) Log in as user with access only to Branch A 2) Try to list/filter Branch B data | G12: — | H12: User sees only Branch A data; no B data visible in lists, reports, dashboards | J12: Not Run
A13: P1-BR-010 | B13: P2 | C13: Positive | D13: Branches | E13: Multiple branches | F13: 1) Use branch switcher in top bar 2) Switch context | G13: — | H13: All subsequent screens reflect selected branch; URL/state updates | J13: Not Run
A14: P1-USR-011 | B14: P1 | C14: Positive | D14: Users | E14: Admin logged in | F14: 1) Users > New 2) Fill Name, Email, Role 3) Save | G14: Email='qa1@test.local', Role='Accountant' | H14: User created; invitation/reset email sent; appears in list | J14: Not Run
A15: P1-USR-012 | B15: P1 | C15: Negative | D15: Users | E15: User qa1@test.local exists | F15: 1) Create user with same email | G15: Email='qa1@test.local' | H15: Duplicate email rejected | J15: Not Run
... A63: P1-TB-060 | B63: P2 | C63: Positive | D63: Audit | E63: Any transaction | F63: 1) Check audit log for: create, edit, post, reverse, delete of JE | G63: — | H63: Each event logged with user, timestamp, before/after diff | J63: Not Run

Sheet Phase 2 Sales & AR
A1: Phase 2 — Sales & Receivables
A2: Total cases: 45 | Fill 'Status' (dropdown). 'Severity' applies only if Fail.
A3: Test ID | B3: Priority | C3: Category | D3: Module / Area | E3: Preconditions | F3: Test Steps | G3: Test Data | H3: Expected Result | I3: Actual Result | J3: Status | K3: Severity (if Fail) | L3: Evidence (URL/path) | M3: Tester | N3: Date | O3: Notes
A4: P2-CUS-001 | B4: P0 | C4: Positive | D4: Customers | E4: Admin logged in | F4: 1) Customers > New 2) Fill Name, Tax No., AR account, Currency 3) Save | G4: Name='Alpha Co', VAT valid, AR=1200 | H4: Customer saved; default AR account applied; unique code | J4: Not Run
A5: P2-CUS-002 | B5: P1 | C5: Negative | D5: Customers | E5: Customer Alpha Co exists | F5: 1) Create duplicate VAT | G5: Same VAT | H5: Rejected | J5: Not Run
A6: P2-CUS-003 | B6: P1 | C6: Positive | D6: Customers | E6: Customer exists | F6: 1) Set credit limit=5,000 SAR | G6: — | H6: Limit stored; visible on customer page | J6: Not Run
A7: P2-CUS-004 | B7: P0 | C7: Integration | D7: Customers | E7: Credit limit 5000 | F7: 1) Issue invoice 6000 SAR for this customer | G7: — | H7: System warns OR blocks based on policy; policy is documented | J7: Not Run
A8: P2-CUS-005 | B8: P1 | C8: Negative | D8: Customers | E8: Inactive customer | F8: 1) Try to select inactive customer on new invoice | G8: — | H8: Not listed / rejected | J8: Not Run
A9: P2-CUS-006 | B9: P2 | C9: Positive | D9: Customers | E9: — | F9: 1) Add multiple addresses (billing/shipping) | G9: — | H9: Both saved and selectable on invoice | J9: Not Run
A10: P2-CUS-007 | B10: P2 | C10: Positive | D10: Customers | E10: Customer with transactions | F10: 1) Try to delete | G10: — | H10: Blocked; deactivate offered | J10: Not Run
A11: P2-INV-008 | B11: P0 | C11: Positive | D11: Invoices | E11: Customer + Item exist | F11: 1) New Invoice 2) Select Alpha Co 3) Add line: Item A, Qty=10, Price=100, Tax=15% 4) Save as Draft | G11: Line total: 1000 + 150 tax = 1150 | H11: Subtotal=1000, Tax=150, Total=1150 computed correctly | J11: Not Run
A12: P2-INV-009 | B12: P1 | C12: Positive | D12: Invoices | E12: — | F12: 1) Invoice with 3 lines, different tax rates, mixed qty | G12: — | H12: Each line computed separately; totals correct; rounding consistent | J12: Not Run
A13: P2-INV-010 | B13: P1 | C13: Positive | D13: Invoices | E13: Line discount 10% | F13: 1) Line: Qty 10 * 100, discount 10% | G13: — | H13: Net=900; tax applied on 900 | J13: Not Run
A14: P2-INV-011 | B14: P1 | C14: Positive | D14: Invoices | E14: Invoice-level discount | F14: 1) Invoice discount 50 SAR | G14: — | H14: Discount applied once; tax base adjusted correctly per policy | J14: Not Run
A15: P2-INV-012 | B15: P2 | C15: Positive | D15: Invoices | E15: FC customer | F15: 1) Create invoice in USD | G15: USD | H15: Amounts in USD; FX applied at posting; AR in both currencies | J15: Not Run
... A48: P2-REC-045 | B48: P1 | C48: Integration | D48: Reconciliation | E48: Multi-branch | F48: 1) Post invoice in Branch A 2) Verify AR of Branch A only affected | G48: — | H48: No cross-branch contamination | J48: Not Run

Sheet Phase 3 Purchases & AP
A1: Phase 3 — Purchases & Payables
A2: Total cases: 40 | Fill 'Status' (dropdown). 'Severity' applies only if Fail.
A3: Test ID | B3: Priority | C3: Category | D3: Module / Area | E3: Preconditions | F3: Test Steps | G3: Test Data | H3: Expected Result | I3: Actual Result | J3: Status | K3: Severity (if Fail) | L3: Evidence (URL/path) | M3: Tester | N3: Date | O3: Notes
A4: P3-VND-001 | B4: P0 | C4: Positive | D4: Vendors | E4: Admin | F4: 1) Vendors > New 2) Fill Name, VAT, AP account 3) Save | G4: Name='Vendor X', VAT valid, AP=2100 | H4: Vendor saved; AP link correct | J4: Not Run
A5: P3-VND-002 | B5: P1 | C5: Negative | D5: Vendors | E5: Vendor X exists | F5: 1) Create duplicate VAT | G5: Duplicate VAT | H5: Rejected | J5: Not Run
A6: P3-VND-003 | B6: P1 | C6: Negative | D6: Vendors | E6: Vendor inactive | F6: 1) Select inactive vendor on new PI | G6: — | H6: Not listed | J6: Not Run
A7: P3-VND-004 | B7: P2 | C7: Positive | D7: Vendors | E7: — | F7: 1) Set vendor payment terms (Net 30) | G7: — | H7: Terms stored; due date auto-calc on PI | J7: Not Run
A8: P3-VND-005 | B8: P1 | C8: Security | D8: Vendors | E8: User in Company A | F8: 1) Try to view vendor of Company B | G8: — | H8: Blocked | J8: Not Run
A9: P3-VND-006 | B9: P2 | C9: Positive | D9: Vendors | E9: Vendor with transactions | F9: 1) Try to delete | G9: — | H9: Blocked; deactivate offered | J9: Not Run
A10: P3-PI-007 | B10: P0 | C10: Positive | D10: Purchase Invoices | E10: Vendor + item exist | F10: 1) New PI 2) Vendor X, Item A, Qty 10 @ 80, VAT 15% 3) Save | G10: Subtotal 800, VAT 120, Total 920 | H10: Totals computed correctly | J10: Not Run
A11: P3-PI-008 | B11: P0 | C11: Integration | D11: Purchase Invoices | E11: PI saved | F11: 1) Post PI 2) Inspect JE | G11: — | H11: JE: Dr Inventory/Expense 800, Dr Input VAT 120, Cr AP 920 | J11: Not Run
A12: P3-PI-009 | B12: P1 | C12: Positive | D12: Purchase Invoices | E12: — | F12: 1) PI with 3 lines, diff tax rates | G12: — | H12: Totals per line + overall correct | J12: Not Run
A13: P3-PI-010 | B13: P1 | C13: Negative | D13: Purchase Invoices | E13: — | F13: 1) PI with zero lines | G13: — | H13: Rejected | J13: Not Run
A14: P3-PI-011 | B14: P1 | C14: Negative | D14: Purchase Invoices | E14: Period closed | F14: 1) Try to post PI in closed period | G14: — | H14: Rejected | J14: Not Run
A15: P3-PI-012 | B15: P0 | C15: Negative | D15: Purchase Invoices | E15: PI posted | F15: 1) Try to edit line amounts | G15: — | H15: Blocked; requires reversal or vendor CN | J15: Not Run
... A43: P3-POS-040 | B43: P0 | C43: Integration | D43: Auto-Posting | E43: Multi-branch | F43: 1) PI in Branch B | G43: — | H43: AP of Branch B only affected; no cross-branch | J43: Not Run

Sheet Phase 4 Treasury
A1: Phase 4 — Treasury / Cash / Bank / Reconciliation
A2: Total cases: 35 | Fill 'Status' (dropdown). 'Severity' applies only if Fail.
A3: Test ID | B3: Priority | C3: Category | D3: Module / Area | E3: Preconditions | F3: Test Steps | G3: Test Data | H3: Expected Result | I3: Actual Result | J3: Status | K3: Severity (if Fail) | L3: Evidence (URL/path) | M3: Tester | N3: Date | O3: Notes
A4: P4-CB-001 | B4: P0 | C4: Positive | D4: Cashboxes | E4: Admin | F4: 1) Treasury > Cashboxes > New 2) Name, Currency, GL account, Branch 3) Save | G4: Cashbox 'Main Cash', SAR, linked to 1010 | H4: Cashbox created; GL link valid | J4: Not Run
A5: P4-CB-002 | B5: P1 | C5: Negative | D5: Cashboxes | E5: Cashbox without GL link | F5: 1) Save | G5: — | H5: Rejected | J5: Not Run
A6: P4-CB-003 | B6: P1 | C6: Negative | D6: Cashboxes | E6: Cashbox is inactive | F6: 1) Try to post cash transaction | G6: — | H6: Rejected | J6: Not Run
A7: P4-CB-004 | B7: P2 | C7: Positive | D7: Cashboxes | E7: Multi-branch | F7: 1) Branch A user cannot use Branch B cashbox | G7: — | H7: Access controlled | J7: Not Run
A8: P4-CB-005 | B8: P1 | C8: Positive | D8: Cashboxes | E8: Cashbox with transactions | F8: 1) Try to delete | G8: — | H8: Blocked; deactivate offered | J8: Not Run
A9: P4-BA-006 | B9: P0 | C9: Positive | D9: Bank Accounts | E9: Admin | F9: 1) New Bank Account 2) IBAN, Swift, Currency, GL | G9: IBAN SA valid | H9: Bank account saved; GL linked | J9: Not Run
A10: P4-BA-007 | B10: P1 | C10: Negative | D10: Bank Accounts | E10: Duplicate IBAN | F10: 1) Create with same IBAN | G10: — | H10: Rejected | J10: Not Run
A11: P4-BA-008 | B11: P1 | C11: Positive | D11: Bank Accounts | E11: FC bank | F11: 1) Create USD bank account | G11: — | H11: Multi-currency supported; revaluation policy documented | J11: Not Run
A12: P4-BA-009 | B12: P2 | C12: Positive | D12: Bank Accounts | E12: Inactive bank | F12: 1) Select on new txn | G12: — | H12: Blocked | J12: Not Run
A13: P4-BA-010 | B13: P0 | C13: Security | D13: Bank Accounts | E13: User without Treasury permission | F13: 1) Try to view bank accounts | G13: — | H13: Blocked at UI and API | J13: Not Run
A14: P4-PM-011 | B14: P1 | C14: Positive | D14: Payment Methods | E14: Admin | F14: 1) Define methods: Cash, Transfer, Check, Card | G14: — | H14: All selectable on receipts/payments | J14: Not Run
A15: P4-PM-012 | B15: P2 | C15: Positive | D15: Payment Methods | E15: — | F15: 1) Link each method to default cash/bank | G15: — | H15: Default propagates correctly | J15: Not Run
... A38: P4-REC-035 | B38: P1 | C38: Negative | D38: Reconciliation | E38: Statement imported | F38: 1) Try reconciliation without matching all required items (duplicate match, negative balances) | G38: — | H38: System prevents invalid state | J38: Not Run

Sheet Phase 5 Inventory
A1: Phase 5 — Inventory / Warehouses / Valuation
A2: Total cases: 40 | Fill 'Status' (dropdown). 'Severity' applies only if Fail.
A3: Test ID | B3: Priority | C3: Category | D3: Module / Area | E3: Preconditions | F3: Test Steps | G3: Test Data | H3: Expected Result | I3: Actual Result | J3: Status | K3: Severity (if Fail) | L3: Evidence (URL/path) | M3: Tester | N3: Date | O3: Notes
A4: P5-ITM-001 | B4: P0 | C4: Positive | D4: Items | E4: Admin | F4: 1) Items > New 2) Code, Name, Type=Stock, UoM, Cost method, GLs 3) Save | G4: Item A, UoM=PC, Cost=Avg | H4: Item saved; GLs linked (Inv, COGS, Sales) | J4: Not Run
A5: P5-ITM-002 | B5: P0 | C5: Positive | D5: Items | E5: — | F5: 1) Create service item (non-stock) | G5: — | H5: No stock tracking; revenue-only mapping | J5: Not Run
A6: P5-ITM-003 | B6: P1 | C6: Negative | D6: Items | E6: Item A exists | F6: 1) Duplicate SKU/code | G6: — | H6: Rejected | J6: Not Run
A7: P5-ITM-004 | B7: P1 | C7: Positive | D7: Items | E7: — | F7: 1) Multi-UoM with conversion factor | G7: Box=12 PCs | H7: Conversions work on txns | J7: Not Run
A8: P5-ITM-005 | B8: P1 | C8: Negative | D8: Items | E8: Item with stock | F8: 1) Try to delete | G8: — | H8: Blocked | J8: Not Run
A9: P5-ITM-006 | B9: P1 | C9: Integration | D9: Items | E9: Item A | F9: 1) Verify cost method enforcement across txns | G9: FIFO or Avg | H9: Consistent cost flow | J9: Not Run
A10: P5-UOM-007 | B10: P1 | C10: Positive | D10: UoM | E10: — | F10: 1) Create UoM: PC, BOX, KG | G10: — | H10: Each saved | J10: Not Run
A11: P5-UOM-008 | B11: P2 | C11: Positive | D11: UoM | E11: — | F11: 1) Conversion PC→BOX | G11: 12:1 | H11: Conversion applied on txns | J11: Not Run
A12: P5-UOM-009 | B12: P2 | C12: Negative | D12: UoM | E12: — | F12: 1) Conversion with 0 or negative factor | G12: — | H12: Rejected | J12: Not Run
A13: P5-CAT-010 | B13: P2 | C13: Positive | D13: Categories | E13: — | F13: 1) Create category 'Electronics' | G13: — | H13: Saved; items assignable | J13: Not Run
A14: P5-CAT-011 | B14: P2 | C14: Integration | D14: Categories | E14: Items in Electronics | F14: 1) Filter inventory report by category | G14: — | H14: Works; totals consistent | J14: Not Run
A15: P5-CAT-012 | B15: P2 | C15: Positive | D15: Categories | E15: — | F15: 1) Rename category | G15: — | H15: Propagates to items | J15: Not Run
... A43: P5-VAL-040 | B43: P2 | C43: Integration | D43: Valuation | E43: FX goods | F43: 1) Import in USD; local cost | G43: — | H43: Cost includes landed cost; currency policy clear | J43: Not Run

Sheet Phase 6 Tax & Closing
A1: Phase 6 — Tax / Closing / Official Financial Reporting
A2: Total cases: 30 | Fill 'Status' (dropdown). 'Severity' applies only if Fail.
A3: Test ID | B3: Priority | C3: Category | D3: Module / Area | E3: Preconditions | F3: Test Steps | G3: Test Data | H3: Expected Result | I3: Actual Result | J3: Status | K3: Severity (if Fail) | L3: Evidence (URL/path) | M3: Tester | N3: Date | O3: Notes
A4: P6-TX-001 | B4: P0 | C4: Positive | D4: Tax Codes | E4: Admin | F4: 1) Tax > New Code 2) VAT 15% Output; linked to 'Output VAT' GL 3) Save | G4: VAT-OUT-15 | H4: Saved; selectable on invoices | J4: Not Run
A5: P6-TX-002 | B5: P0 | C5: Positive | D5: Tax Codes | E5: — | F5: 1) VAT 15% Input / VAT 0% / Exempt | G5: — | H5: All four codes (Out, In, Zero, Exempt) created | J5: Not Run
A6: P6-TX-003 | B6: P1 | C6: Negative | D6: Tax Codes | E6: Invalid rate | F6: 1) Rate >100% or negative | G6: — | H6: Rejected | J6: Not Run
A7: P6-TX-004 | B7: P1 | C7: Positive | D7: Tax Codes | E7: — | F7: 1) Map each code to correct GL | G7: — | H7: No cross-mapping | J7: Not Run
A8: P6-TX-005 | B8: P2 | C8: Positive | D8: Tax Profiles | E8: — | F8: 1) Create tax profile grouping codes | G8: — | H8: Profiles usable on customers/vendors | J8: Not Run
A9: P6-TX-006 | B9: P0 | C9: Integration | D9: Tax Calc | E9: Invoice | F9: 1) Line 100 SAR, VAT 15% exclusive | G9: — | H9: Tax=15; Total=115 | J9: Not Run
A10: P6-TX-007 | B10: P0 | C10: Integration | D10: Tax Calc | E10: Invoice | F10: 1) Line 115 SAR, VAT 15% inclusive | G10: — | H10: Base=100, Tax=15 extracted correctly | J10: Not Run
A11: P6-TX-008 | B11: P1 | C11: Integration | D11: Tax Calc | E11: Line discount 10% | F11: 1) 100 × 10 qty − 10% = 900; VAT 15% | G11: — | H11: Tax on 900 = 135 | J11: Not Run
A12: P6-TX-009 | B12: P1 | C12: Integration | D12: Tax Calc | E12: — | F12: 1) Multi-line with different rates (0/5/15) | G12: — | H12: Each line taxed correctly; totals match | J12: Not Run
A13: P6-TX-010 | B13: P1 | C13: Integration | D13: Tax Calc | E13: Reverse charge (if feature) | F13: 1) PI with reverse charge code | G13: — | H13: Both Input & Output booked; net effect 0 | J13: Not Run
A14: P6-TX-011 | B14: P1 | C14: Integration | D14: Tax Calc | E14: Rounding | F14: 1) Invoice with odd amounts causing fractions | G14: — | H14: Rounding policy consistent & documented | J14: Not Run
A15: P6-TX-012 | B15: P0 | C15: Integration | D15: Tax Report | E15: Invoices + PIs + CNs + VCNs posted | F15: 1) Run VAT return | G15: — | H15: Output VAT − Input VAT = Net payable; matches underlying GL | J15: Not Run
... A33: P6-FS-030 | B33: P0 | C33: Integration | D33: Reports | E33: — | F33: 1) TB totals vs BS totals vs P&L net income | G33: — | H33: All tie out consistently | J33: Not Run

Sheet Phase 7 Smart Finance
A1: Phase 7 — Smart Finance / AI / Audit
A2: Total cases: 25 | Fill 'Status' (dropdown). 'Severity' applies only if Fail.
A3: Test ID | B3: Priority | C3: Category | D3: Module / Area | E3: Preconditions | F3: Test Steps | G3: Test Data | H3: Expected Result | I3: Actual Result | J3: Status | K3: Severity (if Fail) | L3: Evidence (URL/path) | M3: Tester | N3: Date | O3: Notes
A4: P7-AN-001 | B4: P1 | C4: Positive | D4: Anomaly | E4: Seed unusual data | F4: 1) Post 10 round-amount invoices (5000, 10000...) 2) Wait for detection run | G4: — | H4: System flags pattern; anomaly visible in dashboard | J4: Not Run
A5: P7-AN-002 | B5: P1 | C5: Positive | D5: Anomaly | E5: — | F5: 1) Post an invoice far above vendor's 90-day avg | G5: — | H5: Anomaly detected and categorized | J5: Not Run
A6: P7-AN-003 | B6: P1 | C6: Integration | D6: Anomaly | E6: Anomaly flagged | F6: 1) Drill-down from alert to underlying JE/invoice | G6: — | H6: Link works; shows evidence | J6: Not Run
A7: P7-AN-004 | B7: P2 | C7: Positive | D7: Anomaly | E7: False-positive test | F7: 1) Review a normal txn flagged as anomaly | G7: — | H7: System provides reason; user can dismiss with note | J7: Not Run
A8: P7-DUP-005 | B8: P0 | C8: Integration | D8: Duplicate | E8: Two identical PIs intentionally | F8: 1) Create 2nd PI with same vendor, date, amount, ref | G8: — | H8: Duplicate flagged before/after post | J8: Not Run
A9: P7-DUP-006 | B9: P1 | C9: Positive | D9: Duplicate | E9: — | F9: 1) Near-duplicate (same amount, different vendor ref #) | G9: — | H9: Fuzzy match raises warning | J9: Not Run
A10: P7-DUP-007 | B10: P2 | C10: Positive | D10: Duplicate | E10: Flagged pair | F10: 1) Dismiss or mark one as true duplicate | G10: — | H10: Workflow handles both paths | J10: Not Run
A11: P7-RS-008 | B11: P1 | C11: Positive | D11: Risk | E11: — | F11: 1) View risk score for vendor/customer | G11: — | H11: Score 0–100 with breakdown factors visible | J11: Not Run
A12: P7-RS-009 | B12: P1 | C12: Integration | D12: Risk | E12: High-risk vendor | F12: 1) Create PI for high-risk vendor | G12: — | H12: Score contributes to review queue/alert | J12: Not Run
A13: P7-RS-010 | B13: P2 | C13: Positive | D13: Risk | E13: — | F13: 1) Score recomputes as new data arrives | G13: — | H13: Reasonably timely | J13: Not Run
A14: P7-AC-011 | B14: P1 | C14: Positive | D14: Audit | E14: Alert exists | F14: 1) Create case from alert 2) Assign 3) Investigate 4) Close with resolution | G14: — | H14: Case workflow complete; trail preserved | J14: Not Run
A15: P7-AC-012 | B15: P1 | C15: Security | D15: Audit | E15: — | F15: 1) Only authorized roles can close cases | G15: — | H15: RBAC enforced | J15: Not Run
... A28: P7-EXP-025 | B28: P1 | C28: Positive | D28: Explainability | E28: Any smart output | F28: 1) Click 'Why this?' | G28: — | H28: Shows rule/model + inputs used; auditable | J28: Not Run

Sheet X-Cutting UI API Sec
A1: Cross-Cutting — UI/UX, API, Security, Reports, Integrity, Regression
A2: Total cases: 46 | Fill 'Status' (dropdown). 'Severity' applies only if Fail.
A3: Test ID | B3: Priority | C3: Category | D3: Module / Area | E3: Preconditions | F3: Test Steps | G3: Test Data | H3: Expected Result | I3: Actual Result | J3: Status | K3: Severity (if Fail) | L3: Evidence (URL/path) | M3: Tester | N3: Date | O3: Notes
A4: X-UI-001 | B4: P2 | C4: Positive | D4: UI/UX | E4: — | F4: 1) Navigate all modules via sidebar | G4: — | H4: Consistent layout, responsive, no dead links | J4: Not Run
A5: X-UI-002 | B5: P2 | C5: Positive | D5: UI/UX | E5: Arabic user | F5: 1) Toggle to AR (if available) | G5: — | H5: **Per F-005: not found on public pages.** Validate on authenticated pages. Full RTL reflow; no broken alignment | J5: Not Run
A6: X-UI-003 | B6: P2 | C6: Positive | D6: UI/UX | E6: — | F6: 1) Mobile/tablet viewport | G6: — | H6: No overflow, readable, sidebar collapses | J6: Not Run
A7: X-UI-004 | B7: P2 | C7: Positive | D7: UI/UX | E7: — | F7: 1) Trigger validation errors in forms | G7: — | H7: Messages clear, in the right language, indicate field | J7: Not Run
A8: X-UI-005 | B8: P2 | C8: Positive | D8: UI/UX | E8: — | F8: 1) Large lists (>1000 rows) | G8: — | H8: Pagination/virtualization; no freeze | J8: Not Run
A9: X-UI-006 | B9: P2 | C9: Positive | D9: UI/UX | E9: — | F9: 1) Empty states (no data) | G9: — | H9: Friendly messaging with CTA | J9: Not Run
A10: X-UI-007 | B10: P2 | C10: Positive | D10: UI/UX | E10: — | F10: 1) Keyboard nav (Tab, Enter, Esc) | G10: — | H10: All primary flows keyboard accessible | J10: Not Run
A11: X-UI-008 | B11: P3 | C11: Positive | D11: UI/UX | E11: — | F11: 1) Browser matrix: Chrome, Edge, Safari, Firefox | G11: — | H11: All work identically | J11: Not Run
A12: X-API-001 | B12: P1 | C12: Security | D12: API | E12: Unauthenticated | F12: 1) Call any protected endpoint | G12: — | H12: 401 returned; no data leak | J12: Not Run
A13: X-API-002 | B13: P1 | C13: Security | D13: API | E13: Authenticated but not authorized | F13: 1) Call forbidden endpoint | G13: — | H13: 403 | J13: Not Run
A14: X-API-003 | B14: P1 | C14: Negative | D14: API | E14: — | F14: 1) Call non-existent resource | G14: — | H14: 404 (not 500) | J14: Not Run
A15: X-API-004 | B15: P1 | C15: Negative | D15: API | E15: — | F15: 1) Submit invalid JSON/fields | G15: — | H15: 400/422 with descriptive error | J15: Not Run
... A49: X-REG-004 | B49: P0 | C49: Integration | D49: Regression | E49: E2E Closing | F49: 1) All of above, then close period, then verify reports don't change | G49: — | H49: Closing preserves all historical figures | J49: Not Run
